setup.py
grass_script/__init__.py
grass_script/help_me.py
grass_script/log.py
grass_script.egg-info/PKG-INFO
grass_script.egg-info/SOURCES.txt
grass_script.egg-info/dependency_links.txt
grass_script.egg-info/top_level.txt