Metadata-Version: 1.1
Name: grass-script
Version: 0.0.4
Summary: A Python module that is basically a programming language
Home-page: UNKNOWN
Author: TheOnlyWalrus
Author-email: UNKNOWN
License: UNKNOWN
Platform: UNKNOWN
Classifier: Development Status :: 3 - Alpha
Classifier: Programming Language :: Python :: 3
